aoa_torch/__init__.py
aoa_torch/main.py
aoa_torch-0.0.1.dist-info/LICENSE
aoa_torch-0.0.1.dist-info/WHEEL
aoa_torch-0.0.1.dist-info/METADATA
aoa_torch-0.0.1.dist-info/RECORD
